{
  "project_info": {
    "project_number": "1094171860918",
    "project_id": "mental-care-today",
    "storage_bucket": "mental-care-today.appspot.com"
  },
  "client": [
    {
      "client_info": {
        "mobilesdk_app_id": "1:1094171860918:android:65f187ba6f59a0dc4eeb17",
        "android_client_info": {
          "package_name": "com.mentalcaretoday.dev"
        }
      },
      "oauth_client": [
        {
          "client_id": "1094171860918-862sq559qmk7imkebgfn0mku9i5pm2qu.apps.googleusercontent.com",
          "client_type": 3
        }
      ],
      "api_key": [
        {
          "current_key": "AIzaSyCms6X11f74btbCkr7JchFZFkG6RLD985k"
        }
      ],
      "services": {
        "appinvite_service": {
          "other_platform_oauth_client": [
            {
              "client_id": "1094171860918-862sq559qmk7imkebgfn0mku9i5pm2qu.apps.googleusercontent.com",
              "client_type": 3
            }
          ]
        }
      }
    }
  ],
  "configuration_version": "1"
}